mcp_server_obsidian/__init__.py
mcp_server_obsidian/__main__.py
mcp_server_obsidian/server.py
mcp_server_obsidian-0.1.3.dist-info/METADATA
mcp_server_obsidian-0.1.3.dist-info/WHEEL
mcp_server_obsidian-0.1.3.dist-info/entry_points.txt
mcp_server_obsidian-0.1.3.dist-info/RECORD
