Metadata-Version: 2.3
Name: mcp-server-obsidian
Version: 0.1.3
Summary: A Model Context Protocol server providing tools to interact with Obsidian vaults for LLMs
Author: anpigon
License: MIT
Keywords: automation,llm,mcp,obsidian
Classifier: Development Status :: 4 - Beta
Classifier: Intended Audience :: Developers
Classifier: License :: OSI Approved :: MIT License
Classifier: Programming Language :: Python :: 3
Classifier: Programming Language :: Python :: 3.11
Requires-Python: >=3.11
Requires-Dist: aiohttp>=3.11.8
Requires-Dist: click>=8.1.7
Requires-Dist: mcp>=1.0.0
Requires-Dist: pydantic>=2.0.0
